dashvisor/__init__.py
dashvisor/apps.py
dashvisor/server.py
dashvisor/urls.py
dashvisor/utils.py
dashvisor/views.py
dashvisor/backends/__init__.py
dashvisor/backends/base.py
dashvisor/backends/file.py
dashvisor/static/dashvisor/css/bootstrap.min.css
dashvisor/static/dashvisor/css/dataTables.bootstrap4.min.css
dashvisor/static/dashvisor/images/icon.png
dashvisor/static/dashvisor/js/bootstrap.bundle.min.js
dashvisor/static/dashvisor/js/bootstrap.min.js
dashvisor/static/dashvisor/js/dataTables.bootstrap4.min.js
dashvisor/static/dashvisor/js/jquery.dataTables.min.js
dashvisor/static/dashvisor/js/jquery.min.js
dashvisor/static/dashvisor/js/jquery.min.map
dashvisor/static/dashvisor/js/popper.min.js
dashvisor/static/dashvisor/js/supervisor.js
dashvisor/templates/dashvisor/base.html
dashvisor/templates/dashvisor/dashboard.html
dashvisor/templates/dashvisor/modal.html
django_dashvisor_ui-1.1.dist-info/LICENCE
django_dashvisor_ui-1.1.dist-info/METADATA
django_dashvisor_ui-1.1.dist-info/WHEEL
django_dashvisor_ui-1.1.dist-info/top_level.txt
django_dashvisor_ui-1.1.dist-info/RECORD
