Metadata-Version: 2.1
Name: django-dashvisor-ui
Version: 1.1
Summary: Django Supervisor dashboard
Home-page: https://github.com/alexsilva/django-dashvisor-ui
Author: Alex
Author-email: alex@fabricadigital.com.br
License: BSD
Keywords: supervisor,dashboard,remote,control
Platform: any
Classifier: Development Status :: 5 - Production/Stable
Classifier: Environment :: Web Environment
Classifier: Framework :: Django
Classifier: Intended Audience :: Developers
Classifier: Natural Language :: English
Classifier: License :: OSI Approved :: BSD License
Classifier: Operating System :: OS Independent
Classifier: Programming Language :: Python
Classifier: Programming Language :: Python :: 2
Classifier: Programming Language :: Python :: 2.7
Classifier: Programming Language :: Python :: 3
Classifier: Topic :: Utilities
